wikipedia_scraper/__init__.py
wikipedia_scraper/__main__.py
wikipedia_scraper/lib.py
wikipsy-1.2.5.dist-info/LICENSE
wikipsy-1.2.5.dist-info/METADATA
wikipsy-1.2.5.dist-info/WHEEL
wikipsy-1.2.5.dist-info/entry_points.txt
wikipsy-1.2.5.dist-info/top_level.txt
wikipsy-1.2.5.dist-info/RECORD
