Metadata-Version: 2.1
Name: wikipsy
Version: 1.2.5
Summary: Scrape wikipedia to get to psychology/philosophy
Author-email: Jayden Qi <jaydeniqv2@gmail.com>
License: MIT License
Project-URL: Homepage, https://github.com/JayAndJef/wikipedia-scraper
Classifier: License :: OSI Approved :: MIT License
Classifier: Programming Language :: Python
Classifier: Programming Language :: Python :: 3
Requires-Python: >=3.11
License-File: LICENSE
Requires-Dist: requests >=2.31.0
Requires-Dist: typer[all] >=0.9.0
Requires-Dist: beautifulsoup4 >=4.12.2
Requires-Dist: graphviz >=0.20.1
Provides-Extra: dev
Requires-Dist: black ; extra == 'dev'
Requires-Dist: bumpver ; extra == 'dev'
Requires-Dist: pytest ; extra == 'dev'
